[
  {
    "name": "AR1",
    "description": "AR1",
    "url": "https://services.mobile.de/refdata/classes/Car/makes/ASTON%20MARTIN/model/AR1"
  },
  {
    "name": "Cygnet",
    "description": "Cygnet",
    "url": "https://services.mobile.de/refdata/classes/Car/makes/ASTON%20MARTIN/model/Cygnet"
  },
  {
    "name": "DB",
    "description": "DB",
    "url": "https://services.mobile.de/refdata/classes/Car/makes/ASTON%20MARTIN/model/DB"
  },
  {
    "name": "DB11",
    "description": "DB11",
    "url": "https://services.mobile.de/refdata/classes/Car/makes/ASTON%20MARTIN/model/DB11"
  },
  {
    "name": "DB12",
    "description": "DB12",
    "url": "https://services.mobile.de/refdata/classes/Car/makes/ASTON%20MARTIN/model/DB12"
  },
  {
    "name": "DB7",
    "description": "DB7",
    "url": "https://services.mobile.de/refdata/classes/Car/makes/ASTON%20MARTIN/model/DB7"
  },
  {
    "name": "DB9",
    "description": "DB9",
    "url": "https://services.mobile.de/refdata/classes/Car/makes/ASTON%20MARTIN/model/DB9"
  },
  {
    "name": "DBS",
    "description": "DBS",
    "url": "https://services.mobile.de/refdata/classes/Car/makes/ASTON%20MARTIN/model/DBS"
  },
  {
    "name": "DBX",
    "description": "DBX",
    "url": "https://services.mobile.de/refdata/classes/Car/makes/ASTON%20MARTIN/model/DBX"
  },
  {
    "name": "Lagonda",
    "description": "Lagonda",
    "url": "https://services.mobile.de/refdata/classes/Car/makes/ASTON%20MARTIN/model/Lagonda"
  },
  {
    "name": "Rapide",
    "description": "Rapide",
    "url": "https://services.mobile.de/refdata/classes/Car/makes/ASTON%20MARTIN/model/Rapide"
  },
  {
    "name": "V12 Speedster",
    "description": "V12 Speedster",
    "url": "https://services.mobile.de/refdata/classes/Car/makes/ASTON%20MARTIN/model/V12%20Speedster"
  },
  {
    "name": "V12 Vantage",
    "description": "V12 Vantage",
    "url": "https://services.mobile.de/refdata/classes/Car/makes/ASTON%20MARTIN/model/V12%20Vantage"
  },
  {
    "name": "V8 Vantage",
    "description": "V8 Vantage",
    "url": "https://services.mobile.de/refdata/classes/Car/makes/ASTON%20MARTIN/model/V8%20Vantage"
  },
  {
    "name": "Valhalla",
    "description": "Valhalla",
    "url": "https://services.mobile.de/refdata/classes/Car/makes/ASTON%20MARTIN/model/Valhalla"
  },
  {
    "name": "Vanquish",
    "description": "Vanquish",
    "url": "https://services.mobile.de/refdata/classes/Car/makes/ASTON%20MARTIN/model/Vanquish"
  },
  {
    "name": "Virage",
    "description": "Virage",
    "url": "https://services.mobile.de/refdata/classes/Car/makes/ASTON%20MARTIN/model/Virage"
  },
  {
    "name": "ANDERE",
    "description": "Andere",
    "url": "https://services.mobile.de/refdata/classes/Car/makes/ASTON%20MARTIN/model/ANDERE"
  }
]